multi_standard_rx_project/rtl/demapper.v

module demapper(
    input  wire clk,
    input  wire rst,
    input  wire signed [15:0] sym_re,
    input  wire signed [15:0] sym_im,
    input  wire sym_valid,
    input  wire [3:0] mod_type,
    output reg  [7:0] bits_out,
    output reg  bits_valid
);
always @(posedge clk or posedge rst) begin
    if (rst) begin
        bits_out <= 0; bits_valid <= 0;
    end else if (sym_valid) begin
        case(mod_type)
            0: begin // QPSK
                // Python: 00->(1+1j), 01->(-1+1j), 11->(-1-1j), 10->(1-1j)
                // Map: + -> 0, - -> 1
                bits_out[1:0] <= {~(sym_re > 0), ~(sym_im > 0)}; 
            end
            1: begin // 16QAM
                // Python: 00->-3, 01->-1, 10->1, 11->3
                // Thresholds approx 20000 (since 1->10000, 3->30000)
                // Real part
                bits_out[3] <= (sym_re > 0); // MSB: 1 if pos, 0 if neg
                if (sym_re > 0)
                    bits_out[2] <= (sym_re > 20000); // 11 if > 20000
                else
                    bits_out[2] <= (sym_re > -20000); // 01 if > -20000 (i.e. -1)
                
                // Imag part
                bits_out[1] <= (sym_im > 0);
                if (sym_im > 0)
                    bits_out[0] <= (sym_im > 20000);
                else
                    bits_out[0] <= (sym_im > -20000);
            end
        endcase
        bits_valid <= 1;
    end else begin
        bits_valid <= 0;
    end
end
endmodule

multi_standard_rx_project/rtl/sync_detect.v

module sync_detect(
    input  wire clk,
    input  wire rst,
    input  wire signed [15:0] din_re,
    input  wire signed [15:0] din_im,
    input  wire din_valid,
    input  wire [11:0] fft_len,
    output reg  sync_found,
    output reg  [15:0] freq_offset,
    // Export energies for multi-antenna combining
    output wire [63:0] corr_energy_out,
    output wire [63:0] total_energy_out
);

    // Determine delay D based on fft_len
    reg [7:0] delay_len;
    always @(*) begin
        case(fft_len)
            12'd256: delay_len = 16;   // WiFi
            12'd2048: delay_len = 64;  // LTE
            12'd4096: delay_len = 128; // NR
            default: delay_len = 16;
        endcase
    end

    // Input Delay Line (Circular Buffer)
    reg signed [15:0] buf_re [0:127];
    reg signed [15:0] buf_im [0:127];
    reg [6:0] wr_ptr;
    
    wire [6:0] rd_ptr = wr_ptr - delay_len[6:0]; 
    
    // Read from buffer (Async read / Combinational)
    wire signed [15:0] delayed_re = buf_re[rd_ptr];
    wire signed [15:0] delayed_im = buf_im[rd_ptr];

    // Correlation Product (Combinational)
    wire signed [31:0] prod_re = din_re * delayed_re + din_im * delayed_im;
    wire signed [31:0] prod_im = din_im * delayed_re - din_re * delayed_im;
    wire signed [31:0] energy_term = din_re * din_re + din_im * din_im;

    // Delay line for products (Sequential write, Async read)
    reg signed [31:0] prod_re_buf [0:127];
    reg signed [31:0] prod_im_buf [0:127];
    reg signed [31:0] energy_buf [0:127];
    
    wire [6:0] prod_rd_ptr = wr_ptr - delay_len[6:0];

    wire signed [31:0] prod_re_delayed = prod_re_buf[prod_rd_ptr];
    wire signed [31:0] prod_im_delayed = prod_im_buf[prod_rd_ptr];
    wire signed [31:0] energy_delayed  = energy_buf[prod_rd_ptr];

    // Moving Sum Accumulators
    reg signed [47:0] sum_prod_re, sum_prod_im;
    reg signed [47:0] sum_energy;

    // Magnitude Squared Calculation for Detection
    wire [63:0] mag_sq_corr = sum_prod_re*sum_prod_re + sum_prod_im*sum_prod_im;
    wire [63:0] mag_sq_energy = sum_energy * sum_energy;

    assign corr_energy_out  = mag_sq_corr;
    assign total_energy_out = mag_sq_energy;

    integer i;

    always @(posedge clk or posedge rst) begin
        if (rst) begin
            wr_ptr       <= 0;
            sum_prod_re  <= 0;
            sum_prod_im  <= 0;
            sum_energy   <= 0;
            sync_found   <= 0;
            freq_offset  <= 0;
            for(i=0; i<128; i=i+1) begin
                buf_re[i]      <= 0; buf_im[i]      <= 0;
                prod_re_buf[i] <= 0; prod_im_buf[i] <= 0;
                energy_buf[i]  <= 0;
            end
        end else if (din_valid) begin
            // 1. Store new sample
            buf_re[wr_ptr] <= din_re;
            buf_im[wr_ptr] <= din_im;

            // 2. Store instantaneous products
            prod_re_buf[wr_ptr] <= prod_re;
            prod_im_buf[wr_ptr] <= prod_im;
            energy_buf[wr_ptr]  <= energy_term;

            // 3. Update sliding sums with sign-extension to 48 bits
            sum_prod_re <= sum_prod_re
                           + {{16{prod_re[31]}}, prod_re}
                           - {{16{prod_re_delayed[31]}}, prod_re_delayed};
            sum_prod_im <= sum_prod_im
                           + {{16{prod_im[31]}}, prod_im}
                           - {{16{prod_im_delayed[31]}}, prod_im_delayed};
            sum_energy  <= sum_energy
                           + {{16{energy_term[31]}}, energy_term}
                           - {{16{energy_delayed[31]}}, energy_delayed};

            // 4. Local detection (optional if using external combining)
            if (sum_energy > 48'd1000000) begin
                if (mag_sq_corr > (mag_sq_energy >> 1)) begin
                    sync_found <= 1'b1;
                end else begin
                    sync_found <= 1'b0;
                end
            end else begin
                sync_found <= 1'b0;
            end

            wr_ptr <= wr_ptr + 1'b1;
        end
    end
endmodule

multi_standard_rx_project/rtl/mode_ctrl.v

module mode_ctrl(
    input  wire        clk,
    input  wire        rst,
    input  wire [1:0]  mode_sel,    // 00=LTE, 01=NR, 10=Wi-Fi
    output reg  [11:0] fft_len,
    output reg  [7:0]  cp_len,
    output reg  [3:0]  mod_type     // 0=QPSK,1=16QAM
);
always @(posedge clk or posedge rst) begin
    if (rst) begin
        fft_len  <= 1024;
        cp_len   <= 72;
        mod_type <= 0;
    end else begin
        case(mode_sel)
            2'b00: begin fft_len<=2048; cp_len<=144; mod_type<=0; end // LTE
            2'b01: begin fft_len<=4096; cp_len<=288; mod_type<=1; end // NR
            2'b10: begin fft_len<=256;  cp_len<=32;  mod_type<=0; end // Wi-Fi
        endcase
    end
end
endmodule

multi_standard_rx_project/rtl/multi_standard_rx.v

module multi_standard_rx(
    input  wire clk,
    input  wire rst,
    input  wire [1:0] mode_sel,
    // 4x4 MIMO Inputs
    input  wire signed [15:0] din_re_0, input wire signed [15:0] din_im_0,
    input  wire signed [15:0] din_re_1, input wire signed [15:0] din_im_1,
    input  wire signed [15:0] din_re_2, input wire signed [15:0] din_im_2,
    input  wire signed [15:0] din_re_3, input wire signed [15:0] din_im_3,
    input  wire din_valid,
    // 4x4 MIMO Outputs
    output wire [7:0] bits_out_0, output wire bits_valid_0,
    output wire [7:0] bits_out_1, output wire bits_valid_1,
    output wire [7:0] bits_out_2, output wire bits_valid_2,
    output wire [7:0] bits_out_3, output wire bits_valid_3,
    output wire sync_found_combined
);
wire [11:0] fft_len;
wire [7:0]  cp_len;
wire [3:0]  mod_type;

mode_ctrl u_mode_ctrl(.clk(clk), .rst(rst), .mode_sel(mode_sel),
                      .fft_len(fft_len), .cp_len(cp_len), .mod_type(mod_type));

// Sync Detect Instances
wire sync_found_0, sync_found_1, sync_found_2, sync_found_3;
wire [15:0] freq_offset_0, freq_offset_1, freq_offset_2, freq_offset_3; // unused now
wire [63:0] corr_E_0, corr_E_1, corr_E_2, corr_E_3;
wire [63:0] total_E_0, total_E_1, total_E_2, total_E_3;

sync_detect u_sync_0(.clk(clk), .rst(rst), .din_re(din_re_0), .din_im(din_im_0), .din_valid(din_valid), .fft_len(fft_len), .sync_found(sync_found_0), .freq_offset(freq_offset_0), .corr_energy_out(corr_E_0), .total_energy_out(total_E_0));
sync_detect u_sync_1(.clk(clk), .rst(rst), .din_re(din_re_1), .din_im(din_im_1), .din_valid(din_valid), .fft_len(fft_len), .sync_found(sync_found_1), .freq_offset(freq_offset_1), .corr_energy_out(corr_E_1), .total_energy_out(total_E_1));
sync_detect u_sync_2(.clk(clk), .rst(rst), .din_re(din_re_2), .din_im(din_im_2), .din_valid(din_valid), .fft_len(fft_len), .sync_found(sync_found_2), .freq_offset(freq_offset_2), .corr_energy_out(corr_E_2), .total_energy_out(total_E_2));
sync_detect u_sync_3(.clk(clk), .rst(rst), .din_re(din_re_3), .din_im(din_im_3), .din_valid(din_valid), .fft_len(fft_len), .sync_found(sync_found_3), .freq_offset(freq_offset_3), .corr_energy_out(corr_E_3), .total_energy_out(total_E_3));

// MIMO Sync Combination (Energy Sum)
/* verilator lint_off WIDTHEXPAND */
wire [65:0] sum_corr_E  = {2'b0,corr_E_0} + {2'b0,corr_E_1} + {2'b0,corr_E_2} + {2'b0,corr_E_3};
wire [65:0] sum_total_E = {2'b0,total_E_0} + {2'b0,total_E_1} + {2'b0,total_E_2} + {2'b0,total_E_3};
/* verilator lint_on WIDTHEXPAND */

reg sync_combined;
always @(posedge clk or posedge rst) begin
    if (rst) sync_combined <= 0;
    else begin
        if (sum_total_E > 66'd4000000) begin // Higher threshold for 4 antennas (extended width)
             if (sum_corr_E > (sum_total_E >> 1))
                sync_combined <= 1;
             else
                sync_combined <= 0;
        end else begin
            sync_combined <= 0;
        end
    end
end

assign sync_found_combined = sync_combined;

// Demapper Instances (Parallel Processing)
demapper u_demap_0(.clk(clk), .rst(rst), .sym_re(din_re_0), .sym_im(din_im_0), .sym_valid(sync_combined), .mod_type(mod_type), .bits_out(bits_out_0), .bits_valid(bits_valid_0));
demapper u_demap_1(.clk(clk), .rst(rst), .sym_re(din_re_1), .sym_im(din_im_1), .sym_valid(sync_combined), .mod_type(mod_type), .bits_out(bits_out_1), .bits_valid(bits_valid_1));
demapper u_demap_2(.clk(clk), .rst(rst), .sym_re(din_re_2), .sym_im(din_im_2), .sym_valid(sync_combined), .mod_type(mod_type), .bits_out(bits_out_2), .bits_valid(bits_valid_2));
demapper u_demap_3(.clk(clk), .rst(rst), .sym_re(din_re_3), .sym_im(din_im_3), .sym_valid(sync_combined), .mod_type(mod_type), .bits_out(bits_out_3), .bits_valid(bits_valid_3));

endmodule

multi_standard_rx_project/sim/wave.vcd
$version Generated by VerilatedVcd $end
$timescale 1ps $end
 $scope module TOP $end
  $var wire 1 ,! clk $end
  $var wire 1 -! rst $end
  $var wire 2 .! mode_sel [1:0] $end
  $var wire 16 /! din_re_0 [15:0] $end
  $var wire 16 0! din_im_0 [15:0] $end
  $var wire 16 1! din_re_1 [15:0] $end
  $var wire 16 2! din_im_1 [15:0] $end
  $var wire 16 3! din_re_2 [15:0] $end
  $var wire 16 4! din_im_2 [15:0] $end
  $var wire 16 5! din_re_3 [15:0] $end
  $var wire 16 6! din_im_3 [15:0] $end
  $var wire 1 7! din_valid $end
  $var wire 8 8! bits_out_0 [7:0] $end
  $var wire 1 9! bits_valid_0 $end
  $var wire 8 :! bits_out_1 [7:0] $end
  $var wire 1 ;! bits_valid_1 $end
  $var wire 8 <! bits_out_2 [7:0] $end
  $var wire 1 =! bits_valid_2 $end
  $var wire 8 >! bits_out_3 [7:0] $end
  $var wire 1 ?! bits_valid_3 $end
  $var wire 1 @! sync_found_combined $end
  $scope module multi_standard_rx $end
   $var wire 1 ,! clk $end
   $var wire 1 -! rst $end
   $var wire 2 .! mode_sel [1:0] $end
   $var wire 16 /! din_re_0 [15:0] $end
   $var wire 16 0! din_im_0 [15:0] $end
   $var wire 16 1! din_re_1 [15:0] $end
   $var wire 16 2! din_im_1 [15:0] $end
   $var wire 16 3! din_re_2 [15:0] $end
   $var wire 16 4! din_im_2 [15:0] $end
   $var wire 16 5! din_re_3 [15:0] $end
   $var wire 16 6! din_im_3 [15:0] $end
   $var wire 1 7! din_valid $end
   $var wire 8 8! bits_out_0 [7:0] $end
   $var wire 1 9! bits_valid_0 $end
   $var wire 8 :! bits_out_1 [7:0] $end
   $var wire 1 ;! bits_valid_1 $end
   $var wire 8 <! bits_out_2 [7:0] $end
   $var wire 1 =! bits_valid_2 $end
   $var wire 8 >! bits_out_3 [7:0] $end
   $var wire 1 ?! bits_valid_3 $end
   $var wire 1 @! sync_found_combined $end
   $var wire 12 / fft_len [11:0] $end
   $var wire 8 0 cp_len [7:0] $end
   $var wire 4 1 mod_type [3:0] $end
   $var wire 1 2 sync_found_0 $end
   $var wire 1 3 sync_found_1 $end
   $var wire 1 4 sync_found_2 $end
   $var wire 1 5 sync_found_3 $end
   $var wire 16 6 freq_offset_0 [15:0] $end
   $var wire 16 7 freq_offset_1 [15:0] $end
   $var wire 16 8 freq_offset_2 [15:0] $end
   $var wire 16 9 freq_offset_3 [15:0] $end
   $var wire 64 : corr_E_0 [63:0] $end
   $var wire 64 < corr_E_1 [63:0] $end
   $var wire 64 > corr_E_2 [63:0] $end
   $var wire 64 @ corr_E_3 [63:0] $end
   $var wire 64 B total_E_0 [63:0] $end
   $var wire 64 D total_E_1 [63:0] $end
   $var wire 64 F total_E_2 [63:0] $end
   $var wire 64 H total_E_3 [63:0] $end
   $var wire 66 J sum_corr_E [65:0] $end
   $var wire 66 M sum_total_E [65:0] $end
   $var wire 1 P sync_combined $end
   $scope module u_demap_0 $end
    $var wire 1 ,! clk $end
    $var wire 1 -! rst $end
    $var wire 16 /! sym_re [15:0] $end
    $var wire 16 0! sym_im [15:0] $end
    $var wire 1 P sym_valid $end
    $var wire 4 1 mod_type [3:0] $end
    $var wire 8 8! bits_out [7:0] $end
    $var wire 1 9! bits_valid $end
   $upscope $end
   $scope module u_demap_1 $end
    $var wire 1 ,! clk $end
    $var wire 1 -! rst $end
    $var wire 16 1! sym_re [15:0] $end
    $var wire 16 2! sym_im [15:0] $end
    $var wire 1 P sym_valid $end
    $var wire 4 1 mod_type [3:0] $end
    $var wire 8 :! bits_out [7:0] $end
    $var wire 1 ;! bits_valid $end
   $upscope $end
   $scope module u_demap_2 $end
    $var wire 1 ,! clk $end
    $var wire 1 -! rst $end
    $var wire 16 3! sym_re [15:0] $end
    $var wire 16 4! sym_im [15:0] $end
    $var wire 1 P sym_valid $end
    $var wire 4 1 mod_type [3:0] $end
    $var wire 8 <! bits_out [7:0] $end
    $var wire 1 =! bits_valid $end
   $upscope $end
   $scope module u_demap_3 $end
    $var wire 1 ,! clk $end
    $var wire 1 -! rst $end
    $var wire 16 5! sym_re [15:0] $end
    $var wire 16 6! sym_im [15:0] $end
    $var wire 1 P sym_valid $end
    $var wire 4 1 mod_type [3:0] $end
    $var wire 8 >! bits_out [7:0] $end
    $var wire 1 ?! bits_valid $end
   $upscope $end
   $scope module u_mode_ctrl $end
    $var wire 1 ,! clk $end
    $var wire 1 -! rst $end
    $var wire 2 .! mode_sel [1:0] $end
    $var wire 12 / fft_len [11:0] $end
    $var wire 8 0 cp_len [7:0] $end
    $var wire 4 1 mod_type [3:0] $end
   $upscope $end
   $scope module u_sync_0 $end
    $var wire 1 ,! clk $end
    $var wire 1 -! rst $end
    $var wire 16 /! din_re [15:0] $end
    $var wire 16 0! din_im [15:0] $end
    $var wire 1 7! din_valid $end
    $var wire 12 / fft_len [11:0] $end
    $var wire 1 2 sync_found $end
    $var wire 16 6 freq_offset [15:0] $end
    $var wire 64 : corr_energy_out [63:0] $end
    $var wire 64 B total_energy_out [63:0] $end
    $var wire 8 Q delay_len [7:0] $end
    $var wire 7 R wr_ptr [6:0] $end
    $var wire 7 S rd_ptr [6:0] $end
    $var wire 16 T delayed_re [15:0] $end
    $var wire 16 U delayed_im [15:0] $end
    $var wire 32 ' prod_re [31:0] $end
    $var wire 32 ( prod_im [31:0] $end
    $var wire 32 # energy_term [31:0] $end
    $var wire 7 S prod_rd_ptr [6:0] $end
    $var wire 32 V prod_re_delayed [31:0] $end
    $var wire 32 W prod_im_delayed [31:0] $end
    $var wire 32 X energy_delayed [31:0] $end
    $var wire 48 Y sum_prod_re [47:0] $end
    $var wire 48 [ sum_prod_im [47:0] $end
    $var wire 48 ] sum_energy [47:0] $end
    $var wire 64 : mag_sq_corr [63:0] $end
    $var wire 64 B mag_sq_energy [63:0] $end
    $var wire 32 _ i [31:0] $end
   $upscope $end
   $scope module u_sync_1 $end
    $var wire 1 ,! clk $end
    $var wire 1 -! rst $end
    $var wire 16 1! din_re [15:0] $end
    $var wire 16 2! din_im [15:0] $end
    $var wire 1 7! din_valid $end
    $var wire 12 / fft_len [11:0] $end
    $var wire 1 3 sync_found $end
    $var wire 16 7 freq_offset [15:0] $end
    $var wire 64 < corr_energy_out [63:0] $end
    $var wire 64 D total_energy_out [63:0] $end
    $var wire 8 Q delay_len [7:0] $end
    $var wire 7 ` wr_ptr [6:0] $end
    $var wire 7 a rd_ptr [6:0] $end
    $var wire 16 b delayed_re [15:0] $end
    $var wire 16 c delayed_im [15:0] $end
    $var wire 32 ) prod_re [31:0] $end
    $var wire 32 * prod_im [31:0] $end
    $var wire 32 $ energy_term [31:0] $end
    $var wire 7 a prod_rd_ptr [6:0] $end
    $var wire 32 d prod_re_delayed [31:0] $end
    $var wire 32 e prod_im_delayed [31:0] $end
    $var wire 32 f energy_delayed [31:0] $end
    $var wire 48 g sum_prod_re [47:0] $end
    $var wire 48 i sum_prod_im [47:0] $end
    $var wire 48 k sum_energy [47:0] $end
    $var wire 64 < mag_sq_corr [63:0] $end
    $var wire 64 D mag_sq_energy [63:0] $end
    $var wire 32 m i [31:0] $end
   $upscope $end
   $scope module u_sync_2 $end
    $var wire 1 ,! clk $end
    $var wire 1 -! rst $end
    $var wire 16 3! din_re [15:0] $end
    $var wire 16 4! din_im [15:0] $end
    $var wire 1 7! din_valid $end
    $var wire 12 / fft_len [11:0] $end
    $var wire 1 4 sync_found $end
    $var wire 16 8 freq_offset [15:0] $end
    $var wire 64 > corr_energy_out [63:0] $end
    $var wire 64 F total_energy_out [63:0] $end
    $var wire 8 Q delay_len [7:0] $end
    $var wire 7 n wr_ptr [6:0] $end
    $var wire 7 o rd_ptr [6:0] $end
    $var wire 16 p delayed_re [15:0] $end
    $var wire 16 q delayed_im [15:0] $end
    $var wire 32 + prod_re [31:0] $end
    $var wire 32 , prod_im [31:0] $end
    $var wire 32 % energy_term [31:0] $end
    $var wire 7 o prod_rd_ptr [6:0] $end
    $var wire 32 r prod_re_delayed [31:0] $end
    $var wire 32 s prod_im_delayed [31:0] $end
    $var wire 32 t energy_delayed [31:0] $end
    $var wire 48 u sum_prod_re [47:0] $end
    $var wire 48 w sum_prod_im [47:0] $end
    $var wire 48 y sum_energy [47:0] $end
    $var wire 64 > mag_sq_corr [63:0] $end
    $var wire 64 F mag_sq_energy [63:0] $end
    $var wire 32 { i [31:0] $end
   $upscope $end
   $scope module u_sync_3 $end
    $var wire 1 ,! clk $end
    $var wire 1 -! rst $end
    $var wire 16 5! din_re [15:0] $end
    $var wire 16 6! din_im [15:0] $end
    $var wire 1 7! din_valid $end
    $var wire 12 / fft_len [11:0] $end
    $var wire 1 5 sync_found $end
    $var wire 16 9 freq_offset [15:0] $end
    $var wire 64 @ corr_energy_out [63:0] $end
    $var wire 64 H total_energy_out [63:0] $end
    $var wire 8 Q delay_len [7:0] $end
    $var wire 7 | wr_ptr [6:0] $end
    $var wire 7 } rd_ptr [6:0] $end
    $var wire 16 ~ delayed_re [15:0] $end
    $var wire 16 !! delayed_im [15:0] $end
    $var wire 32 - prod_re [31:0] $end
    $var wire 32 . prod_im [31:0] $end
    $var wire 32 & energy_term [31:0] $end
    $var wire 7 } prod_rd_ptr [6:0] $end
    $var wire 32 "! prod_re_delayed [31:0] $end
    $var wire 32 #! prod_im_delayed [31:0] $end
    $var wire 32 $! energy_delayed [31:0] $end
    $var wire 48 %! sum_prod_re [47:0] $end
    $var wire 48 '! sum_prod_im [47:0] $end
    $var wire 48 )! sum_energy [47:0] $end
    $var wire 64 @ mag_sq_corr [63:0] $end
    $var wire 64 H mag_sq_energy [63:0] $end
    $var wire 32 +! i [31:0] $end
   $upscope $end
  $upscope $end
 $upscope $end
$enddefinitions $end


#0
b00000000000000000000000000000000 #
b00000000000000000000000000000000 $
b00000000000000000000000000000000 %
b00000000000000000000000000000000 &
b00000000000000000000000000000000 '
b00000000000000000000000000000000 (
b00000000000000000000000000000000 )
b00000000000000000000000000000000 *
b00000000000000000000000000000000 +
b00000000000000000000000000000000 ,
b00000000000000000000000000000000 -
b00000000000000000000000000000000 .
b000000000000 /
b00000000 0
b0000 1
02
03
04
05
b0000000000000000 6
b0000000000000000 7
b0000000000000000 8
b0000000000000000 9
b0000000000000000000000000000000000000000000000000000000000000000 :
b0000000000000000000000000000000000000000000000000000000000000000 <
b0000000000000000000000000000000000000000000000000000000000000000 >
b0000000000000000000000000000000000000000000000000000000000000000 @
b0000000000000000000000000000000000000000000000000000000000000000 B
b0000000000000000000000000000000000000000000000000000000000000000 D
b0000000000000000000000000000000000000000000000000000000000000000 F
b0000000000000000000000000000000000000000000000000000000000000000 H
b000000000000000000000000000000000000000000000000000000000000000000 J
b000000000000000000000000000000000000000000000000000000000000000000 M
0P
b10000000 Q
b0000000 R
b0000000 S
b0000000000000000 T
b0000000000000000 U
b00000000000000000000000000000000 V
b00000000000000000000000000000000 W
b00000000000000000000000000000000 X
b000000000000000000000000000000000000000000000000 Y
b000000000000000000000000000000000000000000000000 [
b000000000000000000000000000000000000000000000000 ]
b00000000000000000000000000000000 _
b0000000 `
b0000000 a
b0000000000000000 b
b0000000000000000 c
b00000000000000000000000000000000 d
b00000000000000000000000000000000 e
b00000000000000000000000000000000 f
b000000000000000000000000000000000000000000000000 g
b000000000000000000000000000000000000000000000000 i
b000000000000000000000000000000000000000000000000 k
b00000000000000000000000000000000 m
b0000000 n
b0000000 o
b0000000000000000 p
b0000000000000000 q
b00000000000000000000000000000000 r
b00000000000000000000000000000000 s
b00000000000000000000000000000000 t
b000000000000000000000000000000000000000000000000 u
b000000000000000000000000000000000000000000000000 w
b000000000000000000000000000000000000000000000000 y
b00000000000000000000000000000000 {
b0000000 |
b0000000 }
b0000000000000000 ~
b0000000000000000 !!
b00000000000000000000000000000000 "!
b00000000000000000000000000000000 #!
b00000000000000000000000000000000 $!
b000000000000000000000000000000000000000000000000 %!
b000000000000000000000000000000000000000000000000 '!
b000000000000000000000000000000000000000000000000 )!
b00000000000000000000000000000000 +!
0,!
0-!
b00 .!
b0000000000000000 /!
b0000000000000000 0!
b0000000000000000 1!
b0000000000000000 2!
b0000000000000000 3!
b0000000000000000 4!
b0000000000000000 5!
b0000000000000000 6!
17!
b00000000 8!
09!
b00000000 :!
0;!
b00000000 <!
0=!
b00000000 >!
0?!
0@!
#1
b100000000000 /
b10010000 0
b01000000 Q
b0000001 R
b1000001 S
b0000001 `
b1000001 a
b0000001 n
b1000001 o
b0000001 |
b1000001 }
1,!
#2
0,!
#3
b0000010 R
b1000010 S
b0000010 `
b1000010 a
b0000010 n
b1000010 o
b0000010 |
b1000010 }
1,!
#4
0,!
#5
b0000011 R
b1000011 S
b0000011 `
b1000011 a
b0000011 n
b1000011 o
b0000011 |
b1000011 }
1,!
#6
0,!
#7
b0000100 R
b1000100 S
b0000100 `
b1000100 a
b0000100 n
b1000100 o
b0000100 |
b1000100 }
1,!
#8
0,!
#9
b0000101 R
b1000101 S
b0000101 `
b1000101 a
b0000101 n
b1000101 o
b0000101 |
b1000101 }
1,!
#10
0,!
#11
b0000110 R
b1000110 S
b0000110 `
b1000110 a
b0000110 n
b1000110 o
b0000110 |
b1000110 }
1,!
#12
0,!
#13
b0000111 R
b1000111 S
b0000111 `
b1000111 a
b0000111 n
b1000111 o
b0000111 |
b1000111 }
1,!
#14
0,!
#15
b0001000 R
b1001000 S
b0001000 `
b1001000 a
b0001000 n
b1001000 o
b0001000 |
b1001000 }
1,!
#16
0,!
#17
b0001001 R
b1001001 S
b0001001 `
b1001001 a
b0001001 n
b1001001 o
b0001001 |
b1001001 }
1,!
#18
0,!
#19
b0001010 R
b1001010 S
b0001010 `
b1001010 a
b0001010 n
b1001010 o
b0001010 |
b1001010 }
1,!
#20
0,!
#21
b0001011 R
b1001011 S
b0001011 `
b1001011 a
b0001011 n
b1001011 o
b0001011 |
b1001011 }
1,!
#22
0,!
#23
b0001100 R
b1001100 S
b0001100 `
b1001100 a
b0001100 n
b1001100 o
b0001100 |
b1001100 }
1,!
#24
0,!
#25
b0001101 R
b1001101 S
b0001101 `
b1001101 a
b0001101 n
b1001101 o
b0001101 |
b1001101 }
1,!
#26
0,!
#27
b0001110 R
b1001110 S
b0001110 `
b1001110 a
b0001110 n
b1001110 o
b0001110 |
b1001110 }
1,!
#28
0,!
#29
b0001111 R
b1001111 S
b0001111 `
b1001111 a
b0001111 n
b1001111 o
b0001111 |
b1001111 }
1,!
#30
0,!
#31
b0010000 R
b1010000 S
b0010000 `
b1010000 a
b0010000 n
b1010000 o
b0010000 |
b1010000 }
1,!
#32
0,!
#33
b0010001 R
b1010001 S
b0010001 `
b1010001 a
b0010001 n
b1010001 o
b0010001 |
b1010001 }
1,!
#34
0,!
#35
b0010010 R
b1010010 S
b0010010 `
b1010010 a
b0010010 n
b1010010 o
b0010010 |
b1010010 }
1,!
#36
0,!
#37
b0010011 R
b1010011 S
b0010011 `
b1010011 a
b0010011 n
b1010011 o
b0010011 |
b1010011 }
1,!
#38
0,!
#39
b0010100 R
b1010100 S
b0010100 `
b1010100 a
b0010100 n
b1010100 o
b0010100 |
b1010100 }
1,!
#40
b00000101111101011101100110000010 #
b00000101111101011101100110000010 $
b00000101111101011101100110000010 %
b00000101111101011101100110000010 &
0,!
b0001101110011111 /!
b0001101110011111 0!
b0001101110011111 1!
b0001101110011111 2!
b0001101110011111 3!
b0001101110011111 4!
b1110010001100001 5!
b0001101110011111 6!
#41
b0000000000100011100001101001100100011111101000011010011000000100 B
b0000000000100011100001101001100100011111101000011010011000000100 D
b0000000000100011100001101001100100011111101000011010011000000100 F
b0000000000100011100001101001100100011111101000011010011000000100 H
b000000000010001110000110100110010001111110100001101001100000010000 M
b0010101 R
b1010101 S
b000000000000000000000101111101011101100110000010 ]
b0010101 `
b1010101 a
b000000000000000000000101111101011101100110000010 k
b0010101 n
b1010101 o
b000000000000000000000101111101011101100110000010 y
b0010101 |
b1010101 }
b000000000000000000000101111101011101100110000010 )!
1,!
#42
0,!
b1110010001100001 /!
b1110010001100001 0!
b1110010001100001 1!
b0001101110011111 5!
#43
b0000000010001110000110100110010001111110100001101001100000010000 B
b0000000010001110000110100110010001111110100001101001100000010000 D
b0000000010001110000110100110010001111110100001101001100000010000 F
b0000000010001110000110100110010001111110100001101001100000010000 H
b000000001000111000011010011001000111111010000110100110000001000000 M
b0010110 R
b1010110 S
b000000000000000000001011111010111011001100000100 ]
b0010110 `
b1010110 a
b000000000000000000001011111010111011001100000100 k
b0010110 n
b1010110 o
b000000000000000000001011111010111011001100000100 y
b0010110 |
b1010110 }
b000000000000000000001011111010111011001100000100 )!
1,!
#44
0,!
b0001101110011111 0!
b1110010001100001 2!
b1110010001100001 5!
#45
b0000000100111111101110110110001000011100101011101101011000100100 B
b0000000100111111101110110110001000011100101011101101011000100100 D
b0000000100111111101110110110001000011100101011101101011000100100 F
b0000000100111111101110110110001000011100101011101101011000100100 H
b000000010011111110111011011000100001110010101110110101100010010000 M
b0010111 R
b1010111 S
b000000000000000000010001111000011000110010000110 ]
b0010111 `
b1010111 a
b000000000000000000010001111000011000110010000110 k
b0010111 n
b1010111 o
b000000000000000000010001111000011000110010000110 y
b0010111 |
b1010111 }
b000000000000000000010001111000011000110010000110 )!
1,!
#46
0,!
b0001101110011111 /!
b0001101110011111 1!
b1110010001100001 3!
b1110010001100001 4!
#47
b0000001000111000011010011001000111111010000110100110000001000000 B
b0000001000111000011010011001000111111010000110100110000001000000 D
b0000001000111000011010011001000111111010000110100110000001000000 F
b0000001000111000011010011001000111111010000110100110000001000000 H
b000000100011100001101001100100011111101000011010011000000100000000 M
b0011000 R
b1011000 S
b000000000000000000010111110101110110011000001000 ]
b0011000 `
b1011000 a
b000000000000000000010111110101110110011000001000 k
b0011000 n
b1011000 o
b000000000000000000010111110101110110011000001000 y
b0011000 |
b1011000 }
b000000000000000000010111110101110110011000001000 )!
1,!
#48
0,!
b1110010001100001 1!
b0001101110011111 2!
b0001101110011111 4!
b1110010001100001 6!
#49
b0000001101111000001001001111010000010110110010010011011001100100 B
b0000001101111000001001001111010000010110110010010011011001100100 D
b0000001101111000001001001111010000010110110010010011011001100100 F
b0000001101111000001001001111010000010110110010010011011001100100 H
b000000110111100000100100111101000001011011001001001101100110010000 M
b0011001 R
b1011001 S
b000000000000000000011101110011010011111110001010 ]
b0011001 `
b1011001 a
b000000000000000000011101110011010011111110001010 k
b0011001 n
b1011001 o
b000000000000000000011101110011010011111110001010 y
b0011001 |
b1011001 }
b000000000000000000011101110011010011111110001010 )!
1,!
#50
0,!
b1110010001100001 0!
b0001101110011111 1!
b1110010001100001 2!
b0001101110011111 3!
b1110010001100001 4!
b0001101110011111 5!
b0001101110011111 6!
#51
b0000010011111110111011011000100001110010101110110101100010010000 B
b0000010011111110111011011000100001110010101110110101100010010000 D
b0000010011111110111011011000100001110010101110110101100010010000 F
b0000010011111110111011011000100001110010101110110101100010010000 H
b000001001111111011101101100010000111001010111011010110001001000000 M
b0011010 R
b1011010 S
b000000000000000000100011110000110001100100001100 ]
b0011010 `
b1011010 a
b000000000000000000100011110000110001100100001100 k
b0011010 n
b1011010 o
b000000000000000000100011110000110001100100001100 y
b0011010 |
b1011010 }
b000000000000000000100011110000110001100100001100 )!
1,!
#52
0,!
b1110010001100001 /!
b1110010001100001 1!
b0001101110011111 2!
b0001101110011111 4!
#53
b0000011011001100110000110100111100001101111100001100011011000100 B
b0000011011001100110000110100111100001101111100001100011011000100 D
b0000011011001100110000110100111100001101111100001100011011000100 F
b0000011011001100110000110100111100001101111100001100011011000100 H
b000001101100110011000011010011110000110111110000110001101100010000 M
b0011011 R
b1011011 S
b000000000000000000101001101110001111001010001110 ]
b0011011 `
b1011011 a
b000000000000000000101001101110001111001010001110 k
b0011011 n
b1011011 o
b000000000000000000101001101110001111001010001110 y
b0011011 |
b1011011 }
b000000000000000000101001101110001111001010001110 )!
1,!
#54
0,!
b0001101110011111 /!
b0001101110011111 1!
