multi_standard_rx_project/rtl/demapper.v

module demapper(
    input  wire clk,
    input  wire rst,
    input  wire signed [15:0] sym_re,
    input  wire signed [15:0] sym_im,
    input  wire sym_valid,
    input  wire [3:0] mod_type,
    output reg  [7:0] bits_out,
    output reg  bits_valid
);
always @(posedge clk or posedge rst) begin
    if (rst) begin
        bits_out <= 0; bits_valid <= 0;
    end else if (sym_valid) begin
        case(mod_type)
            0: begin // QPSK
                // Python: 00->(1+1j), 01->(-1+1j), 11->(-1-1j), 10->(1-1j)
                // Map: + -> 0, - -> 1
                bits_out[1:0] <= {~(sym_re > 0), ~(sym_im > 0)}; 
            end
            1: begin // 16QAM
                // Python: 00->-3, 01->-1, 10->1, 11->3
                // Thresholds approx 20000 (since 1->10000, 3->30000)
                // Real part
                bits_out[3] <= (sym_re > 0); // MSB: 1 if pos, 0 if neg
                if (sym_re > 0)
                    bits_out[2] <= (sym_re > 20000); // 11 if > 20000
                else
                    bits_out[2] <= (sym_re > -20000); // 01 if > -20000 (i.e. -1)
                
                // Imag part
                bits_out[1] <= (sym_im > 0);
                if (sym_im > 0)
                    bits_out[0] <= (sym_im > 20000);
                else
                    bits_out[0] <= (sym_im > -20000);
            end
        endcase
        bits_valid <= 1;
    end else begin
        bits_valid <= 0;
    end
end
endmodule

multi_standard_rx_project/rtl/sync_detect.v

module sync_detect(
    input  wire clk,
    input  wire rst,
    input  wire config_update, // Atomic update trigger
    input  wire signed [15:0] din_re,
    input  wire signed [15:0] din_im,
    input  wire din_valid,
    input  wire [12:0] fft_len, // Shadow input
    output reg  sync_found,
    output reg  [15:0] freq_offset,
    // Export energies for multi-antenna combining
    output wire [63:0] corr_energy_out,
    output wire [63:0] total_energy_out
);

    // --- Shadow Register Logic ---
    reg [12:0] active_fft_len;
    always @(posedge clk or posedge rst) begin
        if (rst) active_fft_len <= 2048;
        else if (config_update) active_fft_len <= fft_len;
    end

    // Determine delay D based on active_fft_len
    reg [11:0] delay_len;
    always @(*) begin
        case(active_fft_len)
            13'd256: delay_len = 16;   // WiFi
            13'd2048: delay_len = 64;  // LTE
            13'd4096: delay_len = 128; // NR
            default: delay_len = 64;
        endcase
    end

    // --- Large Circular Buffer (Support up to 4096) ---
    reg signed [15:0] buf_re [0:4095];
    reg signed [15:0] buf_im [0:4095];
    reg [11:0] wr_ptr; // 12-bit pointer
    
    wire [11:0] rd_ptr = wr_ptr - delay_len; 
    
    // Read from buffer (Async read / Combinational)
    wire signed [15:0] delayed_re = buf_re[rd_ptr];
    wire signed [15:0] delayed_im = buf_im[rd_ptr];

    // Correlation Product (Combinational)
    wire signed [31:0] prod_re = din_re * delayed_re + din_im * delayed_im;
    wire signed [31:0] prod_im = din_im * delayed_re - din_re * delayed_im;
    wire signed [31:0] energy_term = din_re * din_re + din_im * din_im;

    // Delay line for products (Sequential write, Async read)
    reg signed [31:0] prod_re_buf [0:4095];
    reg signed [31:0] prod_im_buf [0:4095];
    reg signed [31:0] energy_buf [0:4095];
    
    wire [11:0] prod_rd_ptr = wr_ptr - delay_len;

    wire signed [31:0] prod_re_delayed = prod_re_buf[prod_rd_ptr];
    wire signed [31:0] prod_im_delayed = prod_im_buf[prod_rd_ptr];
    wire signed [31:0] energy_delayed  = energy_buf[prod_rd_ptr];

    // Moving Sum Accumulators
    reg signed [47:0] sum_prod_re, sum_prod_im;
    reg signed [47:0] sum_energy;

    // Magnitude Squared Calculation for Detection
    wire [63:0] mag_sq_corr = sum_prod_re*sum_prod_re + sum_prod_im*sum_prod_im;
    wire [63:0] mag_sq_energy = sum_energy * sum_energy;

    assign corr_energy_out  = mag_sq_corr;
    assign total_energy_out = mag_sq_energy;

    integer i;

    always @(posedge clk or posedge rst) begin
        if (rst) begin
            wr_ptr       <= 0;
            sum_prod_re  <= 0;
            sum_prod_im  <= 0;
            sum_energy   <= 0;
            sync_found   <= 0;
            freq_offset  <= 0;
            // Note: Clearing large arrays in reset is omitted for synthesis efficiency
            // In simulation, X values will flush out after 4096 cycles
        end else if (config_update) begin
            // Reset accumulators and state on mode switch
            sum_prod_re  <= 0;
            sum_prod_im  <= 0;
            sum_energy   <= 0;
            sync_found   <= 0;
            // We do not reset wr_ptr to maintain continuity or we could reset it. 
            // Resetting accumulators is critical to avoid energy spikes from mixed modes.
        end else if (din_valid) begin
            // 1. Store new sample
            buf_re[wr_ptr] <= din_re;
            buf_im[wr_ptr] <= din_im;

            // 2. Store instantaneous products
            prod_re_buf[wr_ptr] <= prod_re;
            prod_im_buf[wr_ptr] <= prod_im;
            energy_buf[wr_ptr]  <= energy_term;

            // 3. Update sliding sums with sign-extension to 48 bits
            sum_prod_re <= sum_prod_re
                           + {{16{prod_re[31]}}, prod_re}
                           - {{16{prod_re_delayed[31]}}, prod_re_delayed};
            sum_prod_im <= sum_prod_im
                           + {{16{prod_im[31]}}, prod_im}
                           - {{16{prod_im_delayed[31]}}, prod_im_delayed};
            sum_energy  <= sum_energy
                           + {{16{energy_term[31]}}, energy_term}
                           - {{16{energy_delayed[31]}}, energy_delayed};

            // 4. Local detection (optional if using external combining)
            if (sum_energy > 48'd1000000) begin
                if (mag_sq_corr > (mag_sq_energy >> 1)) begin
                    sync_found <= 1'b1;
                end else begin
                    sync_found <= 1'b0;
                end
            end else begin
                sync_found <= 1'b0;
            end

            wr_ptr <= wr_ptr + 1'b1;
        end
    end
endmodule

multi_standard_rx_project/rtl/mode_ctrl.v

module mode_ctrl(
    input  wire        clk,
    input  wire        rst,
    input  wire [1:0]  mode_sel,    // 00=LTE, 01=NR, 10=Wi-Fi
    
    // Global Control
    output reg         tready_global, // 1=Ready, 0=Pause (Drain/Config)
    output reg         config_update, // Pulse to update shadow registers
    
    // Config Parameters (Shadow inputs to operators)
    output reg  [12:0] fft_len,
    output reg  [8:0]  cp_len,
    output reg  [3:0]  mod_type     // 0=QPSK,1=16QAM
);

    // State definitions
    localparam S_RUN    = 3'd0;
    localparam S_DRAIN  = 3'd1;
    localparam S_CONFIG = 3'd2;
    localparam S_WARMUP = 3'd3;
    
    reg [2:0] state;
    reg [1:0] current_mode;
    reg [7:0] timer;

    // Parameter LUT based on requested mode
    always @(*) begin
        case(mode_sel)
            2'b00: begin fft_len=2048; cp_len=144; mod_type=0; end // LTE
            2'b01: begin fft_len=4096; cp_len=288; mod_type=1; end // NR
            2'b10: begin fft_len=256;  cp_len=32;  mod_type=0; end // Wi-Fi
            default: begin fft_len=2048; cp_len=144; mod_type=0; end
        endcase
    end

    always @(posedge clk or posedge rst) begin
        if (rst) begin
            state <= S_RUN;
            current_mode <= 0; // Default LTE
            tready_global <= 1;
            config_update <= 0;
            timer <= 0;
        end else begin
            case(state)
                S_RUN: begin
                    tready_global <= 1;
                    config_update <= 0;
                    // Detect mode change request
                    if (mode_sel != current_mode) begin
                        state <= S_DRAIN;
                        timer <= 20; // Drain time (simulate pipeline flush)
                    end
                end
                S_DRAIN: begin
                    tready_global <= 0; // Block input
                    if (timer == 0) state <= S_CONFIG;
                    else timer <= timer - 1;
                end
                S_CONFIG: begin
                    config_update <= 1; // Trigger atomic update
                    current_mode <= mode_sel;
                    state <= S_WARMUP;
                    timer <= 50; // Warmup time (simulate PLL/AGC lock)
                end
                S_WARMUP: begin
                    config_update <= 0;
                    if (timer == 0) state <= S_RUN;
                    else timer <= timer - 1;
                end
                default: state <= S_RUN;
            endcase
        end
    end
endmodule

multi_standard_rx_project/rtl/multi_standard_rx.v

module multi_standard_rx(
    input  wire clk,
    input  wire rst,
    input  wire [1:0] mode_sel,
    // 4x4 MIMO Inputs
    input  wire signed [15:0] din_re_0, input wire signed [15:0] din_im_0,
    input  wire signed [15:0] din_re_1, input wire signed [15:0] din_im_1,
    input  wire signed [15:0] din_re_2, input wire signed [15:0] din_im_2,
    input  wire signed [15:0] din_re_3, input wire signed [15:0] din_im_3,
    input  wire din_valid,
    // 4x4 MIMO Outputs
    output wire [7:0] bits_out_0, output wire bits_valid_0,
    output wire [7:0] bits_out_1, output wire bits_valid_1,
    output wire [7:0] bits_out_2, output wire bits_valid_2,
    output wire [7:0] bits_out_3, output wire bits_valid_3,
    output wire sync_found_combined,
    output wire tready_global // New output for flow control
);
wire [12:0] fft_len;
wire [8:0]  cp_len;
wire [3:0]  mod_type;
wire config_update; // Internal signal

mode_ctrl u_mode_ctrl(
    .clk(clk), 
    .rst(rst), 
    .mode_sel(mode_sel),
    .tready_global(tready_global),
    .config_update(config_update),
    .fft_len(fft_len), 
    .cp_len(cp_len), 
    .mod_type(mod_type)
);

// Sync Detect Instances
wire sync_found_0, sync_found_1, sync_found_2, sync_found_3;
wire [15:0] freq_offset_0, freq_offset_1, freq_offset_2, freq_offset_3; // unused now
wire [63:0] corr_E_0, corr_E_1, corr_E_2, corr_E_3;
wire [63:0] total_E_0, total_E_1, total_E_2, total_E_3;

// Pass config_update to sync instances
sync_detect u_sync_0(.clk(clk), .rst(rst), .config_update(config_update), .din_re(din_re_0), .din_im(din_im_0), .din_valid(din_valid), .fft_len(fft_len), .sync_found(sync_found_0), .freq_offset(freq_offset_0), .corr_energy_out(corr_E_0), .total_energy_out(total_E_0));
sync_detect u_sync_1(.clk(clk), .rst(rst), .config_update(config_update), .din_re(din_re_1), .din_im(din_im_1), .din_valid(din_valid), .fft_len(fft_len), .sync_found(sync_found_1), .freq_offset(freq_offset_1), .corr_energy_out(corr_E_1), .total_energy_out(total_E_1));
sync_detect u_sync_2(.clk(clk), .rst(rst), .config_update(config_update), .din_re(din_re_2), .din_im(din_im_2), .din_valid(din_valid), .fft_len(fft_len), .sync_found(sync_found_2), .freq_offset(freq_offset_2), .corr_energy_out(corr_E_2), .total_energy_out(total_E_2));
sync_detect u_sync_3(.clk(clk), .rst(rst), .config_update(config_update), .din_re(din_re_3), .din_im(din_im_3), .din_valid(din_valid), .fft_len(fft_len), .sync_found(sync_found_3), .freq_offset(freq_offset_3), .corr_energy_out(corr_E_3), .total_energy_out(total_E_3));

// MIMO Sync Combination (Energy Sum)
/* verilator lint_off WIDTHEXPAND */
wire [65:0] sum_corr_E  = {2'b0,corr_E_0} + {2'b0,corr_E_1} + {2'b0,corr_E_2} + {2'b0,corr_E_3};
wire [65:0] sum_total_E = {2'b0,total_E_0} + {2'b0,total_E_1} + {2'b0,total_E_2} + {2'b0,total_E_3};
/* verilator lint_on WIDTHEXPAND */

reg sync_combined;
always @(posedge clk or posedge rst) begin
    if (rst) sync_combined <= 0;
    else begin
        if (sum_total_E > 66'd4000000) begin // Higher threshold for 4 antennas (extended width)
             if (sum_corr_E > (sum_total_E >> 1))
                sync_combined <= 1;
             else
                sync_combined <= 0;
        end else begin
            sync_combined <= 0;
        end
    end
end

assign sync_found_combined = sync_combined;

// Demapper Instances (Parallel Processing)
demapper u_demap_0(.clk(clk), .rst(rst), .sym_re(din_re_0), .sym_im(din_im_0), .sym_valid(sync_combined), .mod_type(mod_type), .bits_out(bits_out_0), .bits_valid(bits_valid_0));
demapper u_demap_1(.clk(clk), .rst(rst), .sym_re(din_re_1), .sym_im(din_im_1), .sym_valid(sync_combined), .mod_type(mod_type), .bits_out(bits_out_1), .bits_valid(bits_valid_1));
demapper u_demap_2(.clk(clk), .rst(rst), .sym_re(din_re_2), .sym_im(din_im_2), .sym_valid(sync_combined), .mod_type(mod_type), .bits_out(bits_out_2), .bits_valid(bits_valid_2));
demapper u_demap_3(.clk(clk), .rst(rst), .sym_re(din_re_3), .sym_im(din_im_3), .sym_valid(sync_combined), .mod_type(mod_type), .bits_out(bits_out_3), .bits_valid(bits_valid_3));

endmodule

multi_standard_rx_project/sim/wave.vcd
$version Generated by VerilatedVcd $end
$timescale 1ps $end
 $scope module TOP $end
  $var wire 1 3! clk $end
  $var wire 1 4! rst $end
  $var wire 2 5! mode_sel [1:0] $end
  $var wire 16 6! din_re_0 [15:0] $end
  $var wire 16 7! din_im_0 [15:0] $end
  $var wire 16 8! din_re_1 [15:0] $end
  $var wire 16 9! din_im_1 [15:0] $end
  $var wire 16 :! din_re_2 [15:0] $end
  $var wire 16 ;! din_im_2 [15:0] $end
  $var wire 16 <! din_re_3 [15:0] $end
  $var wire 16 =! din_im_3 [15:0] $end
  $var wire 1 >! din_valid $end
  $var wire 8 ?! bits_out_0 [7:0] $end
  $var wire 1 @! bits_valid_0 $end
  $var wire 8 A! bits_out_1 [7:0] $end
  $var wire 1 B! bits_valid_1 $end
  $var wire 8 C! bits_out_2 [7:0] $end
  $var wire 1 D! bits_valid_2 $end
  $var wire 8 E! bits_out_3 [7:0] $end
  $var wire 1 F! bits_valid_3 $end
  $var wire 1 G! sync_found_combined $end
  $var wire 1 H! tready_global $end
  $scope module multi_standard_rx $end
   $var wire 1 3! clk $end
   $var wire 1 4! rst $end
   $var wire 2 5! mode_sel [1:0] $end
   $var wire 16 6! din_re_0 [15:0] $end
   $var wire 16 7! din_im_0 [15:0] $end
   $var wire 16 8! din_re_1 [15:0] $end
   $var wire 16 9! din_im_1 [15:0] $end
   $var wire 16 :! din_re_2 [15:0] $end
   $var wire 16 ;! din_im_2 [15:0] $end
   $var wire 16 <! din_re_3 [15:0] $end
   $var wire 16 =! din_im_3 [15:0] $end
   $var wire 1 >! din_valid $end
   $var wire 8 ?! bits_out_0 [7:0] $end
   $var wire 1 @! bits_valid_0 $end
   $var wire 8 A! bits_out_1 [7:0] $end
   $var wire 1 B! bits_valid_1 $end
   $var wire 8 C! bits_out_2 [7:0] $end
   $var wire 1 D! bits_valid_2 $end
   $var wire 8 E! bits_out_3 [7:0] $end
   $var wire 1 F! bits_valid_3 $end
   $var wire 1 G! sync_found_combined $end
   $var wire 1 H! tready_global $end
   $var wire 13 # fft_len [12:0] $end
   $var wire 9 $ cp_len [8:0] $end
   $var wire 4 % mod_type [3:0] $end
   $var wire 1 2 config_update $end
   $var wire 1 3 sync_found_0 $end
   $var wire 1 4 sync_found_1 $end
   $var wire 1 5 sync_found_2 $end
   $var wire 1 6 sync_found_3 $end
   $var wire 16 7 freq_offset_0 [15:0] $end
   $var wire 16 8 freq_offset_1 [15:0] $end
   $var wire 16 9 freq_offset_2 [15:0] $end
   $var wire 16 : freq_offset_3 [15:0] $end
   $var wire 64 ; corr_E_0 [63:0] $end
   $var wire 64 = corr_E_1 [63:0] $end
   $var wire 64 ? corr_E_2 [63:0] $end
   $var wire 64 A corr_E_3 [63:0] $end
   $var wire 64 C total_E_0 [63:0] $end
   $var wire 64 E total_E_1 [63:0] $end
   $var wire 64 G total_E_2 [63:0] $end
   $var wire 64 I total_E_3 [63:0] $end
   $var wire 66 K sum_corr_E [65:0] $end
   $var wire 66 N sum_total_E [65:0] $end
   $var wire 1 Q sync_combined $end
   $scope module u_demap_0 $end
    $var wire 1 3! clk $end
    $var wire 1 4! rst $end
    $var wire 16 6! sym_re [15:0] $end
    $var wire 16 7! sym_im [15:0] $end
    $var wire 1 Q sym_valid $end
    $var wire 4 % mod_type [3:0] $end
    $var wire 8 ?! bits_out [7:0] $end
    $var wire 1 @! bits_valid $end
   $upscope $end
   $scope module u_demap_1 $end
    $var wire 1 3! clk $end
    $var wire 1 4! rst $end
    $var wire 16 8! sym_re [15:0] $end
    $var wire 16 9! sym_im [15:0] $end
    $var wire 1 Q sym_valid $end
    $var wire 4 % mod_type [3:0] $end
    $var wire 8 A! bits_out [7:0] $end
    $var wire 1 B! bits_valid $end
   $upscope $end
   $scope module u_demap_2 $end
    $var wire 1 3! clk $end
    $var wire 1 4! rst $end
    $var wire 16 :! sym_re [15:0] $end
    $var wire 16 ;! sym_im [15:0] $end
    $var wire 1 Q sym_valid $end
    $var wire 4 % mod_type [3:0] $end
    $var wire 8 C! bits_out [7:0] $end
    $var wire 1 D! bits_valid $end
   $upscope $end
   $scope module u_demap_3 $end
    $var wire 1 3! clk $end
    $var wire 1 4! rst $end
    $var wire 16 <! sym_re [15:0] $end
    $var wire 16 =! sym_im [15:0] $end
    $var wire 1 Q sym_valid $end
    $var wire 4 % mod_type [3:0] $end
    $var wire 8 E! bits_out [7:0] $end
    $var wire 1 F! bits_valid $end
   $upscope $end
   $scope module u_mode_ctrl $end
    $var wire 1 3! clk $end
    $var wire 1 4! rst $end
    $var wire 2 5! mode_sel [1:0] $end
    $var wire 1 H! tready_global $end
    $var wire 1 2 config_update $end
    $var wire 13 # fft_len [12:0] $end
    $var wire 9 $ cp_len [8:0] $end
    $var wire 4 % mod_type [3:0] $end
    $var wire 3 I! S_RUN [2:0] $end
    $var wire 3 J! S_DRAIN [2:0] $end
    $var wire 3 K! S_CONFIG [2:0] $end
    $var wire 3 L! S_WARMUP [2:0] $end
    $var wire 3 R state [2:0] $end
    $var wire 2 S current_mode [1:0] $end
    $var wire 8 T timer [7:0] $end
   $upscope $end
   $scope module u_sync_0 $end
    $var wire 1 3! clk $end
    $var wire 1 4! rst $end
    $var wire 1 2 config_update $end
    $var wire 16 6! din_re [15:0] $end
    $var wire 16 7! din_im [15:0] $end
    $var wire 1 >! din_valid $end
    $var wire 13 # fft_len [12:0] $end
    $var wire 1 3 sync_found $end
    $var wire 16 7 freq_offset [15:0] $end
    $var wire 64 ; corr_energy_out [63:0] $end
    $var wire 64 C total_energy_out [63:0] $end
    $var wire 13 U active_fft_len [12:0] $end
    $var wire 12 V delay_len [11:0] $end
    $var wire 12 W wr_ptr [11:0] $end
    $var wire 12 X rd_ptr [11:0] $end
    $var wire 16 Y delayed_re [15:0] $end
    $var wire 16 Z delayed_im [15:0] $end
    $var wire 32 * prod_re [31:0] $end
    $var wire 32 + prod_im [31:0] $end
    $var wire 32 & energy_term [31:0] $end
    $var wire 12 X prod_rd_ptr [11:0] $end
    $var wire 32 [ prod_re_delayed [31:0] $end
    $var wire 32 \ prod_im_delayed [31:0] $end
    $var wire 32 ] energy_delayed [31:0] $end
    $var wire 48 ^ sum_prod_re [47:0] $end
    $var wire 48 ` sum_prod_im [47:0] $end
    $var wire 48 b sum_energy [47:0] $end
    $var wire 64 ; mag_sq_corr [63:0] $end
    $var wire 64 C mag_sq_energy [63:0] $end
    $var wire 32 M! i [31:0] $end
   $upscope $end
   $scope module u_sync_1 $end
    $var wire 1 3! clk $end
    $var wire 1 4! rst $end
    $var wire 1 2 config_update $end
    $var wire 16 8! din_re [15:0] $end
    $var wire 16 9! din_im [15:0] $end
    $var wire 1 >! din_valid $end
    $var wire 13 # fft_len [12:0] $end
    $var wire 1 4 sync_found $end
    $var wire 16 8 freq_offset [15:0] $end
    $var wire 64 = corr_energy_out [63:0] $end
    $var wire 64 E total_energy_out [63:0] $end
    $var wire 13 d active_fft_len [12:0] $end
    $var wire 12 e delay_len [11:0] $end
    $var wire 12 f wr_ptr [11:0] $end
    $var wire 12 g rd_ptr [11:0] $end
    $var wire 16 h delayed_re [15:0] $end
    $var wire 16 i delayed_im [15:0] $end
    $var wire 32 , prod_re [31:0] $end
    $var wire 32 - prod_im [31:0] $end
    $var wire 32 ' energy_term [31:0] $end
    $var wire 12 g prod_rd_ptr [11:0] $end
    $var wire 32 j prod_re_delayed [31:0] $end
    $var wire 32 k prod_im_delayed [31:0] $end
    $var wire 32 l energy_delayed [31:0] $end
    $var wire 48 m sum_prod_re [47:0] $end
    $var wire 48 o sum_prod_im [47:0] $end
    $var wire 48 q sum_energy [47:0] $end
    $var wire 64 = mag_sq_corr [63:0] $end
    $var wire 64 E mag_sq_energy [63:0] $end
    $var wire 32 N! i [31:0] $end
   $upscope $end
   $scope module u_sync_2 $end
    $var wire 1 3! clk $end
    $var wire 1 4! rst $end
    $var wire 1 2 config_update $end
    $var wire 16 :! din_re [15:0] $end
    $var wire 16 ;! din_im [15:0] $end
    $var wire 1 >! din_valid $end
    $var wire 13 # fft_len [12:0] $end
    $var wire 1 5 sync_found $end
    $var wire 16 9 freq_offset [15:0] $end
    $var wire 64 ? corr_energy_out [63:0] $end
    $var wire 64 G total_energy_out [63:0] $end
    $var wire 13 s active_fft_len [12:0] $end
    $var wire 12 t delay_len [11:0] $end
    $var wire 12 u wr_ptr [11:0] $end
    $var wire 12 v rd_ptr [11:0] $end
    $var wire 16 w delayed_re [15:0] $end
    $var wire 16 x delayed_im [15:0] $end
    $var wire 32 . prod_re [31:0] $end
    $var wire 32 / prod_im [31:0] $end
    $var wire 32 ( energy_term [31:0] $end
    $var wire 12 v prod_rd_ptr [11:0] $end
    $var wire 32 y prod_re_delayed [31:0] $end
    $var wire 32 z prod_im_delayed [31:0] $end
    $var wire 32 { energy_delayed [31:0] $end
    $var wire 48 | sum_prod_re [47:0] $end
    $var wire 48 ~ sum_prod_im [47:0] $end
    $var wire 48 "! sum_energy [47:0] $end
    $var wire 64 ? mag_sq_corr [63:0] $end
    $var wire 64 G mag_sq_energy [63:0] $end
    $var wire 32 O! i [31:0] $end
   $upscope $end
   $scope module u_sync_3 $end
    $var wire 1 3! clk $end
    $var wire 1 4! rst $end
    $var wire 1 2 config_update $end
    $var wire 16 <! din_re [15:0] $end
    $var wire 16 =! din_im [15:0] $end
    $var wire 1 >! din_valid $end
    $var wire 13 # fft_len [12:0] $end
    $var wire 1 6 sync_found $end
    $var wire 16 : freq_offset [15:0] $end
    $var wire 64 A corr_energy_out [63:0] $end
    $var wire 64 I total_energy_out [63:0] $end
    $var wire 13 $! active_fft_len [12:0] $end
    $var wire 12 %! delay_len [11:0] $end
    $var wire 12 &! wr_ptr [11:0] $end
    $var wire 12 '! rd_ptr [11:0] $end
    $var wire 16 (! delayed_re [15:0] $end
    $var wire 16 )! delayed_im [15:0] $end
    $var wire 32 0 prod_re [31:0] $end
    $var wire 32 1 prod_im [31:0] $end
    $var wire 32 ) energy_term [31:0] $end
    $var wire 12 '! prod_rd_ptr [11:0] $end
    $var wire 32 *! prod_re_delayed [31:0] $end
    $var wire 32 +! prod_im_delayed [31:0] $end
    $var wire 32 ,! energy_delayed [31:0] $end
    $var wire 48 -! sum_prod_re [47:0] $end
    $var wire 48 /! sum_prod_im [47:0] $end
    $var wire 48 1! sum_energy [47:0] $end
    $var wire 64 A mag_sq_corr [63:0] $end
    $var wire 64 I mag_sq_energy [63:0] $end
    $var wire 32 P! i [31:0] $end
   $upscope $end
  $upscope $end
 $upscope $end
$enddefinitions $end


#0
b0100000000000 #
b010010000 $
b0000 %
b00000000000000000000000000000000 &
b00000000000000000000000000000000 '
b00000000000000000000000000000000 (
b00000000000000000000000000000000 )
b00000000000000000000000000000000 *
b00000000000000000000000000000000 +
b00000000000000000000000000000000 ,
b00000000000000000000000000000000 -
b00000000000000000000000000000000 .
b00000000000000000000000000000000 /
b00000000000000000000000000000000 0
b00000000000000000000000000000000 1
02
03
04
05
06
b0000000000000000 7
b0000000000000000 8
b0000000000000000 9
b0000000000000000 :
b0000000000000000000000000000000000000000000000000000000000000000 ;
b0000000000000000000000000000000000000000000000000000000000000000 =
b0000000000000000000000000000000000000000000000000000000000000000 ?
b0000000000000000000000000000000000000000000000000000000000000000 A
b0000000000000000000000000000000000000000000000000000000000000000 C
b0000000000000000000000000000000000000000000000000000000000000000 E
b0000000000000000000000000000000000000000000000000000000000000000 G
b0000000000000000000000000000000000000000000000000000000000000000 I
b000000000000000000000000000000000000000000000000000000000000000000 K
b000000000000000000000000000000000000000000000000000000000000000000 N
0Q
b000 R
b00 S
b00000000 T
b0000000000000 U
b000001000000 V
b000000000000 W
b111111000000 X
b0000000000000000 Y
b0000000000000000 Z
b00000000000000000000000000000000 [
b00000000000000000000000000000000 \
b00000000000000000000000000000000 ]
b000000000000000000000000000000000000000000000000 ^
b000000000000000000000000000000000000000000000000 `
b000000000000000000000000000000000000000000000000 b
b0000000000000 d
b000001000000 e
b000000000000 f
b111111000000 g
b0000000000000000 h
b0000000000000000 i
b00000000000000000000000000000000 j
b00000000000000000000000000000000 k
b00000000000000000000000000000000 l
b000000000000000000000000000000000000000000000000 m
b000000000000000000000000000000000000000000000000 o
b000000000000000000000000000000000000000000000000 q
b0000000000000 s
b000001000000 t
b000000000000 u
b111111000000 v
b0000000000000000 w
b0000000000000000 x
b00000000000000000000000000000000 y
b00000000000000000000000000000000 z
b00000000000000000000000000000000 {
b000000000000000000000000000000000000000000000000 |
b000000000000000000000000000000000000000000000000 ~
b000000000000000000000000000000000000000000000000 "!
b0000000000000 $!
b000001000000 %!
b000000000000 &!
b111111000000 '!
b0000000000000000 (!
b0000000000000000 )!
b00000000000000000000000000000000 *!
b00000000000000000000000000000000 +!
b00000000000000000000000000000000 ,!
b000000000000000000000000000000000000000000000000 -!
b000000000000000000000000000000000000000000000000 /!
b000000000000000000000000000000000000000000000000 1!
03!
04!
b00 5!
b0000000000000000 6!
b0000000000000000 7!
b0000000000000000 8!
b0000000000000000 9!
b0000000000000000 :!
b0000000000000000 ;!
b0000000000000000 <!
b0000000000000000 =!
0>!
b00000000 ?!
0@!
b00000000 A!
0B!
b00000000 C!
0D!
b00000000 E!
0F!
0G!
0H!
b000 I!
b001 J!
b010 K!
b011 L!
b00000000000000000000000000000000 M!
b00000000000000000000000000000000 N!
b00000000000000000000000000000000 O!
b00000000000000000000000000000000 P!
#1
13!
1H!
#2
03!
1>!
#3
b000000000001 W
b111111000001 X
b000000000001 f
b111111000001 g
b000000000001 u
b111111000001 v
b000000000001 &!
b111111000001 '!
13!
#4
03!
#5
b000000000010 W
b111111000010 X
b000000000010 f
b111111000010 g
b000000000010 u
b111111000010 v
b000000000010 &!
b111111000010 '!
13!
#6
03!
#7
b000000000011 W
b111111000011 X
b000000000011 f
b111111000011 g
b000000000011 u
b111111000011 v
b000000000011 &!
b111111000011 '!
13!
#8
03!
#9
b000000000100 W
b111111000100 X
b000000000100 f
b111111000100 g
b000000000100 u
b111111000100 v
b000000000100 &!
b111111000100 '!
13!
#10
03!
#11
b000000000101 W
b111111000101 X
b000000000101 f
b111111000101 g
b000000000101 u
b111111000101 v
b000000000101 &!
b111111000101 '!
13!
#12
03!
#13
b000000000110 W
b111111000110 X
b000000000110 f
b111111000110 g
b000000000110 u
b111111000110 v
b000000000110 &!
b111111000110 '!
13!
#14
03!
#15
b000000000111 W
b111111000111 X
b000000000111 f
b111111000111 g
b000000000111 u
b111111000111 v
b000000000111 &!
b111111000111 '!
13!
#16
03!
#17
b000000001000 W
b111111001000 X
b000000001000 f
b111111001000 g
b000000001000 u
b111111001000 v
b000000001000 &!
b111111001000 '!
13!
#18
03!
#19
b000000001001 W
b111111001001 X
b000000001001 f
b111111001001 g
b000000001001 u
b111111001001 v
b000000001001 &!
b111111001001 '!
13!
#20
03!
#21
b000000001010 W
b111111001010 X
b000000001010 f
b111111001010 g
b000000001010 u
b111111001010 v
b000000001010 &!
b111111001010 '!
13!
#22
03!
#23
b000000001011 W
b111111001011 X
b000000001011 f
b111111001011 g
b000000001011 u
b111111001011 v
b000000001011 &!
b111111001011 '!
13!
#24
03!
#25
b000000001100 W
b111111001100 X
b000000001100 f
b111111001100 g
b000000001100 u
b111111001100 v
b000000001100 &!
b111111001100 '!
13!
#26
03!
#27
b000000001101 W
b111111001101 X
b000000001101 f
b111111001101 g
b000000001101 u
b111111001101 v
b000000001101 &!
b111111001101 '!
13!
#28
03!
#29
b000000001110 W
b111111001110 X
b000000001110 f
b111111001110 g
b000000001110 u
b111111001110 v
b000000001110 &!
b111111001110 '!
13!
#30
03!
#31
b000000001111 W
b111111001111 X
b000000001111 f
b111111001111 g
b000000001111 u
b111111001111 v
b000000001111 &!
b111111001111 '!
13!
#32
03!
#33
b000000010000 W
b111111010000 X
b000000010000 f
b111111010000 g
b000000010000 u
b111111010000 v
b000000010000 &!
b111111010000 '!
13!
#34
03!
#35
b000000010001 W
b111111010001 X
b000000010001 f
b111111010001 g
b000000010001 u
b111111010001 v
b000000010001 &!
b111111010001 '!
13!
#36
03!
#37
b000000010010 W
b111111010010 X
b000000010010 f
b111111010010 g
b000000010010 u
b111111010010 v
b000000010010 &!
b111111010010 '!
13!
#38
03!
#39
b000000010011 W
b111111010011 X
b000000010011 f
b111111010011 g
b000000010011 u
b111111010011 v
b000000010011 &!
b111111010011 '!
13!
#40
03!
#41
b000000010100 W
b111111010100 X
b000000010100 f
b111111010100 g
b000000010100 u
b111111010100 v
b000000010100 &!
b111111010100 '!
13!
#42
b00000101111101011101100110000010 &
b00000101111101011101100110000010 '
b00000101111101011101100110000010 (
b00000101111101011101100110000010 )
03!
b0001101110011111 6!
b0001101110011111 7!
b0001101110011111 8!
b0001101110011111 9!
b1110010001100001 :!
b1110010001100001 ;!
b0001101110011111 <!
b1110010001100001 =!
#43
b0000000000100011100001101001100100011111101000011010011000000100 C
b0000000000100011100001101001100100011111101000011010011000000100 E
b0000000000100011100001101001100100011111101000011010011000000100 G
b0000000000100011100001101001100100011111101000011010011000000100 I
b000000000010001110000110100110010001111110100001101001100000010000 N
b000000010101 W
b111111010101 X
b000000000000000000000101111101011101100110000010 b
b000000010101 f
b111111010101 g
b000000000000000000000101111101011101100110000010 q
b000000010101 u
b111111010101 v
b000000000000000000000101111101011101100110000010 "!
b000000010101 &!
b111111010101 '!
b000000000000000000000101111101011101100110000010 1!
13!
#44
03!
b1110010001100001 6!
b1110010001100001 8!
b0001101110011111 :!
b0001101110011111 ;!
b1110010001100001 <!
b0001101110011111 =!
#45
b0000000010001110000110100110010001111110100001101001100000010000 C
b0000000010001110000110100110010001111110100001101001100000010000 E
b0000000010001110000110100110010001111110100001101001100000010000 G
b0000000010001110000110100110010001111110100001101001100000010000 I
b000000001000111000011010011001000111111010000110100110000001000000 N
b000000010110 W
b111111010110 X
b000000000000000000001011111010111011001100000100 b
b000000010110 f
b111111010110 g
b000000000000000000001011111010111011001100000100 q
b000000010110 u
b111111010110 v
b000000000000000000001011111010111011001100000100 "!
b000000010110 &!
b111111010110 '!
b000000000000000000001011111010111011001100000100 1!
13!
